{
  "id": "eden-hazard",
  "name": "Eden Hazard",
  "club": "Chelsea",
  "goals": 85,
  "appearances": 245,
  "seasons": [
    "2012-13",
    "2013-14",
    "2014-15",
    "2015-16",
    "2016-17",
    "2017-18",
    "2018-19"
  ],
  "seasonStats": [
    {
      "season": "2012-13",
      "goals": 9,
      "club": "Chelsea"
    },
    {
      "season": "2013-14",
      "goals": 14,
      "club": "Chelsea"
    },
    {
      "season": "2014-15",
      "goals": 14,
      "club": "Chelsea"
    },
    {
      "season": "2015-16",
      "goals": 4,
      "club": "Chelsea"
    },
    {
      "season": "2016-17",
      "goals": 16,
      "club": "Chelsea"
    },
    {
      "season": "2017-18",
      "goals": 12,
      "club": "Chelsea"
    },
    {
      "season": "2018-19",
      "goals": 16,
      "club": "Chelsea"
    }
  ]
}